{"name":"Blackandwhite","tagline":"","body":"O modelo abaixo é do exercício 1 de POO2 que consiste em aplicar o padrão de projeto \"Fabrica abstrata\".  \r\n\r\n1)No padrão Abstract Factory, ou Fábrica Abstrata, a aplicação interage com uma 'fábrica genérica de objetos‘ os objetos serão gerados efetivamente pela fábrica concreta que estiver sendo utilizada no momento.\r\nIntenção: fornecer uma interface para a criação de famílias de objetos relacionados ou dependentes sem especificar suas classes.\r\nAplicabilidade: aplicável a situações nas quais\r\n– o sistema deve ser independente de como seus produtos são criados, compostos ou representados;\r\n– o sistema deve ser configurado como um produto de uma família de múltiplos produtos;\r\n– a ‘família’ de objetos-produto é projetada para ser usada em conjunto;\r\n– deseja-se revelar apenas a interface da biblioteca de classes-produto e não a sua implementação completas;\r\n\r\n2)A intenção do padrão segundo:\r\n“Separar a construção de um objeto complexo de sua representação de modo que o mesmo processo de construção possa criar diferentes representações.”\r\nSeparar a construção da representação segue a mesma ideia dos padrões Factory Method e Abstract Factory. No entanto o padrão Builder permite separar os passos de construção de um objeto em pequenos métodos. Então vamos direto ao código para ver o que muda.No padrão Builder temos também uma interface comum para todos os objetos que constroem outros objetos. Essa interface Builder define todos os passos necessários para construir um objeto(essa classe no código é chamada de Builder()).\r\n\r\n3)O padrão Factory Method encapsula a criação de objetos, no entanto, a diferença é que neste padrão encapsula-se a criação de objetos deixando as subclasses decidirem quais objetos criar. Este padrão foi aplicado na classe Promocional().\r\n\r\n4)Singleton é um padrão de projeto de software. Este padrão garante a existência de apenas uma instância de uma classe, mantendo um ponto global de acesso ao seu objeto. Aplicado também na classe Promocional() para garantir a existência de apenas uma instância.\r\n\r\nExplicação do modelo:\r\n\r\nA interface Fabrica possui dois metodos, criarCafe() e criarIngredientes(), a classe FabricaCafeAbstrata fica encarregada de implementa-la. As classes FabricaCafeNormal, FabricaCafeSemCafeina e FabricaCappucino herdam os atributos e metodos da classe FabricaCafeAbstrata. As classes FabricaCafe, Cafe e Ingrediente usam o classe Fabrica.\r\n![](https://raw.githubusercontent.com/brunomergh/BlackandWhite/master/Modelo/BlackWhite.png)\r\n\r\nModelo após o Padrão Builder:\r\n![](https://raw.githubusercontent.com/brunomergh/BlackandWhite/master/Modelo/BlackWhiteBuilder.png)","google":"","note":"Don't delete this file! It's used internally to help with page regeneration."}